{
  "name": "buyers",
  "base": "PersistedModel",
  "idInjection": true,
  "options": {
    "validateUpsert": true
  },
  "properties": {
    "fname": {
      "type": "string",
      "required": true
    },
    "lname": {
      "type": "string",
      "required": true
    },
    "email": {
      "type": "string",
      "required": true
    },
    "postcode": {
      "type": "number",
      "required": true
    },
    "cost": {
      "type": "number",
      "required": true
    }
  },
  "validations": [],
  "relations": {},
  "acls": [],
  "methods": {}
}
